karel_for_synthesis
