Metadata-Version: 2.1
Name: karel-for-synthesis
Version: 1.4.0
Summary: Karel Parser and Executor useful for program synthesis.
Home-page: https://github.com/kavigupta/karel-for-synthesis
Author-email: karel_for_synthesis@kavigupta.org
License: UNKNOWN
Platform: UNKNOWN
Classifier: Programming Language :: Python :: 3.6
Classifier: Programming Language :: Python :: 3.7
Classifier: Programming Language :: Python :: 3.8
Classifier: Operating System :: OS Independent
Requires-Python: >=3.6
